README.rst
setup.py
ChronologerUI.egg-info/PKG-INFO
ChronologerUI.egg-info/SOURCES.txt
ChronologerUI.egg-info/dependency_links.txt
ChronologerUI.egg-info/requires.txt
ChronologerUI.egg-info/top_level.txt
chronologerui/__init__.py
chronologerui/static/index.html
chronologerui/static/resource/ace/ace.js
chronologerui/static/resource/ace/mode-yaml.js
chronologerui/static/resource/ace/theme-textmate.js
chronologerui/static/resource/clui/image/loading66.gif
chronologerui/static/resource/clui/image/logo/logo64.png
chronologerui/static/resource/clui/style/timeline.css
chronologerui/static/resource/kucken/image/loading16.gif
chronologerui/static/resource/qx/decoration/Simple/arrows/down-invert.gif
chronologerui/static/resource/qx/decoration/Simple/arrows/down-small.gif
chronologerui/static/resource/qx/decoration/Simple/arrows/down.gif
chronologerui/static/resource/qx/decoration/Simple/arrows/forward.gif
chronologerui/static/resource/qx/decoration/Simple/arrows/left-invert.gif
chronologerui/static/resource/qx/decoration/Simple/arrows/left.gif
chronologerui/static/resource/qx/decoration/Simple/arrows/rewind.gif
chronologerui/static/resource/qx/decoration/Simple/arrows/right-invert.gif
chronologerui/static/resource/qx/decoration/Simple/arrows/right.gif
chronologerui/static/resource/qx/decoration/Simple/arrows/up-invert.gif
chronologerui/static/resource/qx/decoration/Simple/arrows/up-small.gif
chronologerui/static/resource/qx/decoration/Simple/arrows/up.gif
chronologerui/static/resource/qx/decoration/Simple/checkbox/checked-disabled.png
chronologerui/static/resource/qx/decoration/Simple/checkbox/checked.png
chronologerui/static/resource/qx/decoration/Simple/checkbox/undetermined-disabled.png
chronologerui/static/resource/qx/decoration/Simple/checkbox/undetermined.png
chronologerui/static/resource/qx/decoration/Simple/colorselector/brightness-field.png
chronologerui/static/resource/qx/decoration/Simple/colorselector/brightness-handle.gif
chronologerui/static/resource/qx/decoration/Simple/colorselector/huesaturation-field.jpg
chronologerui/static/resource/qx/decoration/Simple/colorselector/huesaturation-handle.gif
