Metadata-Version: 1.1
Name: ChronologerUI
Version: 0.4.1
Summary: Graphical user interface for the Python HTTP logging server
Home-page: https://bitbucket.org/saaj/chronologer/src/frontend
Author: saaj
Author-email: mail@saaj.me
License: GPL-3.0
Platform: Any
Classifier: Framework :: CherryPy
Classifier: Programming Language :: Python :: 3
Classifier: Programming Language :: Python :: 3 :: Only
Classifier: Programming Language :: Python :: Implementation :: CPython
Classifier: Intended Audience :: Developers
